py_log/__init__.py
py_log/handlers.py
py_log/log_manager.py
py_log/monkey_print.py
py_log/py_log_config_default.py
py_log/set_nb_log_config.py
py_log/test.py
py_log-2.5.dist-info/METADATA
py_log-2.5.dist-info/WHEEL
py_log-2.5.dist-info/top_level.txt
py_log-2.5.dist-info/RECORD
