Metadata-Version: 2.1
Name: py-log
Version: 2.5
Summary: a simple logging tool(support file,email,dingtalk) ,Multithreading and Multi process safe
Home-page: https://github.com/abo123456789/py-log
Author: bfzs
Author-email: ydf0509@sohu.com
Maintainer: abo123456
Maintainer-email: abcdef123456chen@sohu.com
License: BSD License
Keywords: logging,logger,multiprocess file handler,color handler
Platform: all
Classifier: Development Status :: 4 - Beta
Classifier: Operating System :: OS Independent
Classifier: Intended Audience :: Developers
Classifier: License :: OSI Approved :: BSD License
Classifier: Programming Language :: Python
Classifier: Programming Language :: Python :: Implementation
Classifier: Programming Language :: Python :: 3.6
Classifier: Topic :: Software Development :: Libraries
Requires-Dist: pymongo (==3.5.1)
Requires-Dist: tomorrow3 (==1.1.0)
Requires-Dist: concurrent-log-handler (==0.9.9)
Requires-Dist: elasticsearch
Requires-Dist: kafka-python (==1.4.6)
Requires-Dist: requests
Requires-Dist: pika
